px/__init__.py
px/px.py
px/px_category_bar.py
px/px_commandline.py
px/px_cpuinfo.py
px/px_cwdfriends.py
px/px_exec_util.py
px/px_file.py
px/px_install.py
px/px_ioload.py
px/px_ipc_map.py
px/px_launchcounter.py
px/px_load.py
px/px_loginhistory.py
px/px_meminfo.py
px/px_pager.py
px/px_poller.py
px/px_process.py
px/px_process_menu.py
px/px_processinfo.py
px/px_sort_order.py
px/px_terminal.py
px/px_top.py
px/px_tree.py
px/px_units.py
px/version.py
pxpx-3.9.0.data/data/share/man/man1/ptop.1
pxpx-3.9.0.data/data/share/man/man1/px.1
pxpx-3.9.0.data/data/share/man/man1/pxtree.1
pxpx-3.9.0.dist-info/licenses/LICENSE
pxpx-3.9.0.dist-info/METADATA
pxpx-3.9.0.dist-info/WHEEL
pxpx-3.9.0.dist-info/entry_points.txt
pxpx-3.9.0.dist-info/top_level.txt
pxpx-3.9.0.dist-info/RECORD
