Metadata-Version: 2.4
Name: pxpx
Version: 3.9.0
Summary: ps and top for Human Beings
Author-email: Johan Walles <johan.walles@gmail.com>
License-Expression: MIT
Project-URL: Homepage, https://github.com/walles/px
Classifier: Development Status :: 5 - Production/Stable
Classifier: Environment :: Console
Classifier: Intended Audience :: System Administrators
Classifier: Operating System :: MacOS
Classifier: Operating System :: POSIX :: Linux
Classifier: Programming Language :: Python :: 3
Classifier: Topic :: System :: Monitoring
Classifier: Topic :: System :: Systems Administration
Classifier: Topic :: Utilities
Requires-Python: >=3.9
License-File: LICENSE
Dynamic: license-file
